llama_api_client/__init__.py
llama_api_client/_base_client.py
llama_api_client/_client.py
llama_api_client/_compat.py
llama_api_client/_constants.py
llama_api_client/_exceptions.py
llama_api_client/_files.py
llama_api_client/_models.py
llama_api_client/_qs.py
llama_api_client/_resource.py
llama_api_client/_response.py
llama_api_client/_streaming.py
llama_api_client/_types.py
llama_api_client/_version.py
llama_api_client/_wrappers.py
llama_api_client/py.typed
llama_api_client/_utils/__init__.py
llama_api_client/_utils/_compat.py
llama_api_client/_utils/_datetime_parse.py
llama_api_client/_utils/_logs.py
llama_api_client/_utils/_proxy.py
llama_api_client/_utils/_reflection.py
llama_api_client/_utils/_resources_proxy.py
llama_api_client/_utils/_streams.py
llama_api_client/_utils/_sync.py
llama_api_client/_utils/_transform.py
llama_api_client/_utils/_typing.py
llama_api_client/_utils/_utils.py
llama_api_client/lib/.keep
llama_api_client/resources/__init__.py
llama_api_client/resources/models.py
llama_api_client/resources/moderations.py
llama_api_client/resources/uploads.py
llama_api_client/resources/chat/__init__.py
llama_api_client/resources/chat/chat.py
llama_api_client/resources/chat/completions.py
llama_api_client/types/__init__.py
llama_api_client/types/completion_message.py
llama_api_client/types/completion_message_param.py
llama_api_client/types/create_chat_completion_response.py
llama_api_client/types/create_chat_completion_response_stream_chunk.py
llama_api_client/types/llama_model.py
llama_api_client/types/message_image_content_item_param.py
llama_api_client/types/message_param.py
llama_api_client/types/message_text_content_item.py
llama_api_client/types/message_text_content_item_param.py
llama_api_client/types/model_list_response.py
llama_api_client/types/moderation_create_params.py
llama_api_client/types/moderation_create_response.py
llama_api_client/types/system_message_param.py
llama_api_client/types/tool_response_message_param.py
llama_api_client-0.6.0.dist-info/METADATA
llama_api_client-0.6.0.dist-info/WHEEL
llama_api_client-0.6.0.dist-info/licenses/LICENSE
llama_api_client-0.6.0.dist-info/RECORD
